fich/__init__.py
fich/__main__.py
fich/arg_parser.py
fich/clean_op.py
fich/cli.py
fich/delete_op.py
fich/exception.py
fich/file_op.py
fich/hash_op.py
fich/info_op.py
fich/path_manager.py
fich/printing.py
fich-0.5.dist-info/LICENSE
fich-0.5.dist-info/METADATA
fich-0.5.dist-info/WHEEL
fich-0.5.dist-info/entry_points.txt
fich-0.5.dist-info/top_level.txt
fich-0.5.dist-info/RECORD
