Metadata-Version: 2.1
Name: fich
Version: 0.5
Summary: Suppression sécurisée et hashage.
Home-page: https://github.com/grolip/fich
Author: grolip
License: UNKNOWN
Project-URL: Source, https://github.com/grolip/fich
Platform: UNKNOWN
Classifier: Environment :: Console
Classifier: Natural Language :: French
Classifier: Development Status :: 4 - Beta
Classifier: Programming Language :: Python :: 3.4
Classifier: Programming Language :: Python :: 3.5
Classifier: Programming Language :: Python :: 3.6
Classifier: Programming Language :: Python :: 3.7
Classifier: License :: OSI Approved :: MIT License
Classifier: Intended Audience :: End Users/Desktop
Classifier: Intended Audience :: System Administrators
Classifier: Operating System :: POSIX :: Linux
Classifier: Topic :: System :: Filesystems
Classifier: Topic :: Utilities
